raiseorlaunch/__init__.py
raiseorlaunch/__main__.py
raiseorlaunch/raiseorlaunch.py
raiseorlaunch-2.3.5.dist-info/LICENSE.txt
raiseorlaunch-2.3.5.dist-info/METADATA
raiseorlaunch-2.3.5.dist-info/WHEEL
raiseorlaunch-2.3.5.dist-info/entry_points.txt
raiseorlaunch-2.3.5.dist-info/top_level.txt
raiseorlaunch-2.3.5.dist-info/RECORD
