Metadata-Version: 2.1
Name: raiseorlaunch
Version: 2.3.5
Summary: A run-or-raise-application-launcher for i3 window manager.
Home-page: https://github.com/open-dynaMIX/raiseorlaunch
Author: Fabio Ambauen
License: MIT
Keywords: i3 i3wm launcher run-or-raise navigation workspace scratchpad
Platform: UNKNOWN
Classifier: Development Status :: 4 - Beta
Classifier: Intended Audience :: End Users/Desktop
Classifier: License :: OSI Approved :: MIT License
Classifier: Programming Language :: Python :: 3.6
Classifier: Programming Language :: Python :: 3.7
Classifier: Programming Language :: Python :: 3.8
Classifier: Programming Language :: Python :: 3.9
Classifier: Programming Language :: Python :: 3.10
Classifier: Programming Language :: Python :: Implementation :: PyPy
License-File: LICENSE.txt
Requires-Dist: i3ipc
